{
  "data": [
    {
      "sentence": "但是还是同时出现的，并没有逐个句子出现。",
      "translation_result": {
        "grammar_explanation": "本句由两个分句构成，以逗号分隔。第一分句\"但是还是同时出现的\"中，\"但是\"作转折连词引导整句，\"还是\"作副词表示\"仍然\"，\"同时\"作时间副词修饰谓语动词\"出现\"，句末助词\"的\"用于强调陈述语气。第二分句\"并没有逐个句子出现\"中，\"并\"为加强否定语气的副词，与\"没有\"构成强否定结构，\"逐个句子\"作方式状语修饰动词\"出现\"，表示动作发生的方式。全句为转折复句，强调内容是\"同时出现\"而非\"逐句出现\"。",
        "tokenized_translation": "但是还是同时出现的，并没有逐个句子出现。",
        "translation": [
          {
            "morphology": "conj",
            "phonetic": "dàn shì",
            "text": "但是",
            "translation": "但是"
          },
          {
            "morphology": "adv",
            "phonetic": "hái shì",
            "text": "还是",
            "translation": "还是"
          },
          {
            "morphology": "adv",
            "phonetic": "tóng shí",
            "text": "同时",
            "translation": "同时"
          },
          {
            "morphology": "v",
            "phonetic": "chū xiàn",
            "text": "出现",
            "translation": "出现"
          },
          {
            "morphology": "adv",
            "phonetic": "de",
            "text": "的",
            "translation": "的"
          },
          {
            "morphology": "adv",
            "phonetic": "bìng",
            "text": "并",
            "translation": "并"
          },
          {
            "morphology": "adv",
            "phonetic": "méi yǒu",
            "text": "没有",
            "translation": "没有"
          },
          {
            "morphology": "adv",
            "phonetic": "zhú gè",
            "text": "逐个",
            "translation": "逐个"
          },
          {
            "morphology": "n",
            "phonetic": "jù zi",
            "text": "句子",
            "translation": "句子"
          },
          {
            "morphology": "v",
            "phonetic": "chū xiàn",
            "text": "出现",
            "translation": "出现"
          }
        ],
        "tokenized_translation_quoted": "\"但是\", \"还是\", \"同时\", \"出现\", \"的\", \"并\", \"没有\", \"逐个\", \"句子\", \"出现\""
      }
    },
    {
      "sentence": "我想要逐个出现的效果，不然等待太久了。",
      "translation_result": {
        "grammar_explanation": "本句由两个分句构成，以连词\"不然（否则）\"连接，表达条件与结果的逻辑关系。第一分句\"我想要逐个出现的效果\"中，\"我\"作主语，\"想要\"作谓语动词，\"逐个出现的效果\"作宾语，其中\"逐个出现的\"为定语修饰名词\"效果\"，\"逐个\"作副词修饰动词\"出现\"。第二分句\"不然等待太久了\"省略主语，\"等待\"作谓语，\"太久\"作程度补语，语气助词\"了\"置于句末，表示对当前状态的感叹或强调，带有轻微抱怨或说明的语气。",
        "tokenized_translation": "我想要逐个出现的效果，否则等待时间太久了。",
        "translation": [
          {
            "morphology": "pron",
            "phonetic": "wǒ",
            "text": "我",
            "translation": "我"
          },
          {
            "morphology": "v",
            "phonetic": "xiǎng yào",
            "text": "想要",
            "translation": "想要"
          },
          {
            "morphology": "adv",
            "phonetic": "zhú gè",
            "text": "逐个",
            "translation": "一个接一个地"
          },
          {
            "morphology": "v",
            "phonetic": "chū xiàn",
            "text": "出现",
            "translation": "出现"
          },
          {
            "morphology": "prep",
            "phonetic": "de",
            "text": "的",
            "translation": "的（结构助词）"
          },
          {
            "morphology": "n",
            "phonetic": "xiào guǒ",
            "text": "效果",
            "translation": "效果"
          },
          {
            "morphology": "conj",
            "phonetic": "bù rán",
            "text": "不然",
            "translation": "否则"
          },
          {
            "morphology": "v",
            "phonetic": "děng dài",
            "text": "等待",
            "translation": "等待"
          },
          {
            "morphology": "adv",
            "phonetic": "tài",
            "text": "太",
            "translation": "太"
          },
          {
            "morphology": "adj",
            "phonetic": "jiǔ",
            "text": "久",
            "translation": "久"
          },
          {
            "morphology": "interj",
            "phonetic": "le",
            "text": "了",
            "translation": "了（语气助词）"
          }
        ],
        "tokenized_translation_quoted": "\"我\", \"想要\", \"一个接一个地\", \"出现\", \"的结构助词\", \"效果\", \"否则\", \"等待\", \"太\", \"久\", \"了语气助词\""
      }
    },
    {
      "sentence": "还有对于单词你并没有查重，还有你并没有按照单词表顺序排列单词。",
      "translation_result": {
        "grammar_explanation": "本句由两个并列分句组成，通过\"还有\"连接，构成递进关系。第一分句\"对于单词你并没有查重\"以介词短语\"对于单词\"作话题引入，主语为\"你\"，副词\"并没有\"加强否定语气，谓语为动词\"查重\"。第二分句\"你并没有按照单词表顺序排列单词\"结构相同，主语仍为\"你\"，\"按照单词表顺序\"为介词短语作状语，修饰谓语动词\"排列\"，宾语为\"单词\"。两个分句共同表达对同一对象（\"你\"）两项操作失误的指出与批评。",
        "tokenized_translation": "另外，对于单词你并没有查重，而且你也没有按照单词表的顺序排列单词。",
        "translation": [
          {
            "morphology": "conj",
            "phonetic": "hái yǒu",
            "text": "还有",
            "translation": "另外"
          },
          {
            "morphology": "prep",
            "phonetic": "duì yú",
            "text": "对于",
            "translation": "关于"
          },
          {
            "morphology": "n",
            "phonetic": "dān cí",
            "text": "单词",
            "translation": "词语"
          },
          {
            "morphology": "pron",
            "phonetic": "nǐ",
            "text": "你",
            "translation": "你"
          },
          {
            "morphology": "adv",
            "phonetic": "bìng méi yǒu",
            "text": "并没有",
            "translation": "根本没有"
          },
          {
            "morphology": "v",
            "phonetic": "chá chóng",
            "text": "查重",
            "translation": "检查重复"
          },
          {
            "morphology": "conj",
            "phonetic": "hái yǒu",
            "text": "还有",
            "translation": "而且"
          },
          {
            "morphology": "pron",
            "phonetic": "nǐ",
            "text": "你",
            "translation": "你"
          },
          {
            "morphology": "adv",
            "phonetic": "bìng méi yǒu",
            "text": "并没有",
            "translation": "根本没有"
          },
          {
            "morphology": "prep",
            "phonetic": "àn zhào",
            "text": "按照",
            "translation": "依照"
          },
          {
            "morphology": "n",
            "phonetic": "dān cí biǎo",
            "text": "单词表",
            "translation": "词汇表"
          },
          {
            "morphology": "n",
            "phonetic": "shùn xù",
            "text": "顺序",
            "translation": "次序"
          },
          {
            "morphology": "v",
            "phonetic": "pái liè",
            "text": "排列",
            "translation": "排序"
          },
          {
            "morphology": "n",
            "phonetic": "dān cí",
            "text": "单词",
            "translation": "词语"
          }
        ],
        "tokenized_translation_quoted": "\"另外\", \"关于\", \"词语\", \"你\", \"根本没有\", \"检查重复\", \"而且\", \"你\", \"根本没有\", \"依照\", \"词汇表\", \"次序\", \"排序\", \"词语\""
      }
    },
    {
      "sentence": "还有单词表右上方的那个按钮有bug，按的越多前几个单词就复制的越多，直接改成顺序和倒序的按钮好了",
      "translation_result": {
        "grammar_explanation": "这是一段功能性缺陷反馈句，由两个分句构成。第一分句\"单词表右上方的那个按钮有bug\"是主谓结构，主语为\"单词表右上方的那个按钮\"（名词短语，由方位词\"右上方\"修饰），谓语为\"有bug\"（存现动词\"有\"带名词宾语\"bug\"）。第二分句\"按的越多前几个单词就复制的越多\"采用\"越…就越…\"的递进关联结构，表达条件与结果之间的正比例关系，即点击行为的频率与复制错误的数量成正比。最后\"直接改成顺序和倒序的按钮好了\"是提出建议的祈使句，副词\"直接\"修饰动词\"改成\"，\"好了\"作语气助词，表达说话人认为此方案简单可行、语气较为随意自然，带有口语化色彩。",
        "tokenized_translation": "另外，单词表右上角的那个按钮存在漏洞，点击次数越多，前几个单词就会被重复复制越多次，建议直接将其改为正序和倒序切换按钮就好了。",
        "translation": [
          {
            "morphology": "conj",
            "phonetic": "hái yǒu",
            "text": "还有",
            "translation": "另外，还有"
          },
          {
            "morphology": "n",
            "phonetic": "dān cí biǎo",
            "text": "单词表",
            "translation": "单词列表"
          },
          {
            "morphology": "n",
            "phonetic": "yòu shàng fāng",
            "text": "右上方",
            "translation": "右上角位置"
          },
          {
            "morphology": "prep",
            "phonetic": "de",
            "text": "的",
            "translation": "的（结构助词）"
          },
          {
            "morphology": "det",
            "phonetic": "nà gè",
            "text": "那个",
            "translation": "那个"
          },
          {
            "morphology": "n",
            "phonetic": "àn niǔ",
            "text": "按钮",
            "translation": "按钮"
          },
          {
            "morphology": "v",
            "phonetic": "yǒu",
            "text": "有",
            "translation": "存在，有"
          },
          {
            "morphology": "n",
            "phonetic": "bʌɡ",
            "text": "bug",
            "translation": "程序错误，漏洞"
          },
          {
            "morphology": "v",
            "phonetic": "àn",
            "text": "按",
            "translation": "点击，按下"
          },
          {
            "morphology": "prep",
            "phonetic": "de",
            "text": "的",
            "translation": "的（结构助词）"
          },
          {
            "morphology": "adv",
            "phonetic": "yuè duō",
            "text": "越多",
            "translation": "次数越多"
          },
          {
            "morphology": "det",
            "phonetic": "qián jǐ gè",
            "text": "前几个",
            "translation": "最前面的几个"
          },
          {
            "morphology": "n",
            "phonetic": "dān cí",
            "text": "单词",
            "translation": "词汇，单词"
          },
          {
            "morphology": "adv",
            "phonetic": "jiù",
            "text": "就",
            "translation": "就会"
          },
          {
            "morphology": "v",
            "phonetic": "fù zhì",
            "text": "复制",
            "translation": "复制，重复"
          },
          {
            "morphology": "prep",
            "phonetic": "de",
            "text": "的",
            "translation": "的（结构助词）"
          },
          {
            "morphology": "adv",
            "phonetic": "yuè duō",
            "text": "越多",
            "translation": "越来越多"
          },
          {
            "morphology": "adv",
            "phonetic": "zhí jiē",
            "text": "直接",
            "translation": "直接，干脆"
          },
          {
            "morphology": "v",
            "phonetic": "gǎi chéng",
            "text": "改成",
            "translation": "修改为，换成"
          },
          {
            "morphology": "n",
            "phonetic": "shùn xù",
            "text": "顺序",
            "translation": "正序，升序"
          },
          {
            "morphology": "conj",
            "phonetic": "hé",
            "text": "和",
            "translation": "和，与"
          },
          {
            "morphology": "n",
            "phonetic": "dào xù",
            "text": "倒序",
            "translation": "逆序，降序"
          },
          {
            "morphology": "prep",
            "phonetic": "de",
            "text": "的",
            "translation": "的（结构助词）"
          },
          {
            "morphology": "n",
            "phonetic": "àn niǔ",
            "text": "按钮",
            "translation": "按钮"
          },
          {
            "morphology": "interj",
            "phonetic": "hǎo le",
            "text": "好了",
            "translation": "就好了，算了"
          }
        ],
        "tokenized_translation_quoted": "\"另外还有\", \"单词列表\", \"右上角位置\", \"的结构助词\", \"那个\", \"按钮\", \"存在有\", \"程序错误漏洞\", \"点击按下\", \"的结构助词\", \"次数越多\", \"最前面的几个\", \"词汇单词\", \"就会\", \"复制重复\", \"的结构助词\", \"越来越多\", \"直接干脆\", \"修改为换成\", \"正序升序\", \"和与\", \"逆序降序\", \"的结构助词\", \"按钮\", \"就好了算了\""
      }
    }
  ]
}