{
  "sentences": {
    "grammar_explanation": "本句 \"Hello world.\" 是一个简单的感叹/问候句，结构极为简洁，由两个部分组成：感叹词 \"Hello\"（你好）和名词 \"world\"（世界）。其中 \"world\" 充当**呼语**（vocative），即说话者直接呼唤或称呼的对象。整句没有主语、谓语或宾语，属于**省略句**（elliptical sentence）或**呼语句**，在语法上完整依赖语境理解。句末使用句号表示陈述语气，而非感叹号，语气相对平静。此句在编程领域常作为入门示例程序的输出内容，具有广泛的文化象征意义。",
    "original": "Hello world.",
    "tokenized_translation": "你好 世界",
    "translation": [
      {
        "morphology": "感叹词（interjection）——用于打招呼的问候语，无词形变化",
        "phonetic": "/həˈloʊ/",
        "text": "Hello",
        "translation": "你好"
      },
      {
        "morphology": "名词（noun）——普通名词，单数形式，在句中作呼语（vocative）",
        "phonetic": "/wɜːrld/",
        "text": "world",
        "translation": "世界"
      }
    ]
  }
}